{
  "type": "object",
  "description": "The chunking strategy used to chunk the file(s). If not set, will use the `auto` strategy. Only applicable if `file_ids` is non-empty.",
  "x-oaiExpandable": true,
  "anyOf": [
    {
      "type": "object",
      "title": "Auto Chunking Strategy",
      "description": "The default strategy. This strategy currently uses a `max_chunk_size_tokens` of `800` and `chunk_overlap_tokens` of `400`.",
      "additionalProperties": false,
      "properties": {
        "type": {
          "type": "string",
          "description": "Always `auto`.",
          "enum": [
            "auto"
          ]
        }
      },
      "required": [
        "type"
      ]
    }
  ],
  "properties": {}
}