{
  "type": "object",
  "properties": {
    "instanceId": {
      "type": "string"
    },
    "projectId": {
      "type": "string"
    },
    "groupName": {
      "description": "Name of the groups that should be deleted",
      "items": {
        "type": "string"
      },
      "type": "array"
    },
    "Authorization": {
      "description": "Accepts technical credentials and api gateway access.",
      "type": "string"
    }
  },
  "required": [
    "instanceId",
    "projectId",
    "groupName",
    "Authorization"
  ]
}