{
  "type": "object",
  "properties": {
    "accessToken": {
      "type": "string",
      "xml": {
        "attribute": true
      }
    },
    "accessTokenKey": {
      "type": "string",
      "xml": {
        "attribute": true
      }
    },
    "clientId": {
      "type": "string",
      "xml": {
        "attribute": true
      }
    },
    "clientSecret": {
      "type": "string",
      "xml": {
        "attribute": true
      }
    },
    "useRefreshToken": {
      "type": "boolean",
      "xml": {
        "attribute": true
      }
    }
  }
}