{
  "additionalProperties": {
    "type": "string"
  },
  "description": "A set of key and value pairs for general use by the account holder or merchant.\nThe keys do not have specific names and may be used for storing miscellaneous data as desired.\n> The values being stored have a maximum length of eighty (80) characters and will be truncated if necessary.\n> Note that during an update of metadata, the omission of existing key-value pairs will result in the deletion of those key-value pairs.",
  "type": "object",
  "properties": {}
}