{
  "type": "object",
  "properties": {
    "id": {
      "description": "The case ID",
      "type": "string"
    },
    "attachmentIds": {
      "description": "A list of attachment IDs from case notes. Case Management supports up to 5 attachments per note. Each attachment should only be associated with one note.",
      "example": [
        "dc294b2b-f671-4868-a8fd-1cd547e420af"
      ],
      "items": {
        "type": "string"
      },
      "type": "array",
      "uniqueItems": false
    },
    "comment": {
      "description": "A comment added to the note",
      "example": "Please see the attached file.",
      "maxLength": 1048576,
      "type": "string"
    }
  },
  "required": [
    "id",
    "comment"
  ]
}